fabric_package_management/__init__.py
fabric_package_management/apt.py
fabric_package_management-0.1.2.dist-info/DESCRIPTION.rst
fabric_package_management-0.1.2.dist-info/METADATA
fabric_package_management-0.1.2.dist-info/RECORD
fabric_package_management-0.1.2.dist-info/WHEEL
fabric_package_management-0.1.2.dist-info/metadata.json
fabric_package_management-0.1.2.dist-info/top_level.txt
tests/__init__.py
tests/test_apt.py
