Metadata-Version: 2.0
Name: fabric-package-management
Version: 0.1.2
Summary: A collection of fabric tasks for package management
Home-page: https://github.com/andrewsomething/fabric-package-management
Author: Andrew Starr-Bochicchio
Author-email: a.starr.b@gmail.com
License: MIT License (Expat)
Download-URL: https://github.com/andrewsomething/fabric-package-management/releases
Platform: UNKNOWN
Requires-Dist: fabric
